arge_consumption/__init__.py
arge_consumption/client.py
arge_consumption/errors.py
arge_consumption/responses.py
arge_consumption-1.0.2.dist-info/WHEEL
arge_consumption-1.0.2.dist-info/METADATA
arge_consumption-1.0.2.dist-info/RECORD
