Metadata-Version: 2.1
Name: arge-consumption
Version: 1.0.2
Summary: Python Client zum Abruf unterjähriger Verbrauchsinformationen über die *ARGE consumption-data API*.
Home-page: https://github.com/Debakel/arge-consumption
Author: Moritz Duchêne
Author-email: 2857237+Debakel@users.noreply.github.com
Requires-Python: >=3.8,<4.0
Classifier: Programming Language :: Python :: 3
Classifier: Programming Language :: Python :: 3.10
Classifier: Programming Language :: Python :: 3.8
Classifier: Programming Language :: Python :: 3.9
Requires-Dist: pydantic (>=1.9.0,<2.0.0)
Requires-Dist: requests (>=2.27.1,<3.0.0)
Project-URL: Repository, https://github.com/Debakel/arge-consumption
